orcalab/__init__.py
orcalab/actor.py
orcalab/actor_property.py
orcalab/actor_util.py
orcalab/application_bus.py
orcalab/application_util.py
orcalab/asset_service.py
orcalab/asset_service_bus.py
orcalab/asset_sync_service.py
orcalab/asset_sync_ui.py
orcalab/auth_service.py
orcalab/cli_options.py
orcalab/config_service.py
orcalab/default_layout.py
orcalab/event_bus.py
orcalab/exception.py
orcalab/launcher.py
orcalab/level_discovery.py
orcalab/local_scene.py
orcalab/logging_util.py
orcalab/main.py
orcalab/math.py
orcalab/metadata_service.py
orcalab/metadata_service_bus.py
orcalab/orca.config.platform_linux.toml
orcalab/orca.config.platform_win32.toml
orcalab/orca.config.template.toml
orcalab/orca.config.toml
orcalab/patch_pyside6.py
orcalab/path.py
orcalab/process_guard.py
orcalab/project_util.py
orcalab/pyside_util.py
orcalab/python_project_installer.py
orcalab/remote_scene.py
orcalab/scene_edit_bus.py
orcalab/scene_edit_service.py
orcalab/scene_layout_converter.py
orcalab/shared_lock.py
orcalab/token_storage.py
orcalab/assets/assets.qrc
orcalab/assets/gen.py
orcalab/assets/rc_assets.py
orcalab/assets/icons/ic_fluent_add_20_filled.svg
orcalab/assets/icons/ic_fluent_arrow_move_20_filled.svg
orcalab/assets/icons/ic_fluent_box_20_regular.svg
orcalab/assets/icons/ic_fluent_camera_20_regular.svg
orcalab/assets/icons/ic_fluent_chat_sparkle_20_regular.svg
orcalab/assets/icons/ic_fluent_checkbox_checked_20_regular.svg
orcalab/assets/icons/ic_fluent_checkbox_unchecked_20_regular.svg
orcalab/assets/icons/ic_fluent_chevron_down_20_filled.svg
orcalab/assets/icons/ic_fluent_chevron_left_20_filled.svg
orcalab/assets/icons/ic_fluent_chevron_right_20_filled.svg
orcalab/assets/icons/ic_fluent_chevron_up_20_filled.svg
orcalab/assets/icons/ic_fluent_circle_edit_20_regular.svg
orcalab/assets/icons/ic_fluent_cube_rotate_20_filled.svg
orcalab/assets/icons/ic_fluent_eye_20_regular.svg
orcalab/assets/icons/ic_fluent_eye_off_20_regular.svg
orcalab/assets/icons/ic_fluent_filter_20_filled.svg
orca_lab-26.1.8.dist-info/METADATA
orca_lab-26.1.8.dist-info/WHEEL
orca_lab-26.1.8.dist-info/entry_points.txt
orca_lab-26.1.8.dist-info/top_level.txt
orca_lab-26.1.8.dist-info/RECORD
