Metadata-Version: 2.4
Name: orca-lab
Version: 26.1.8
Summary: OrcaLab - Cloud-native robotics simulation platform with advanced UI and asset management
Author-email: 松应科技 <huangwei@orca3d.cn>
License: MIT
Project-URL: Homepage, https://github.com/openverse-orca/OrcaLab
Project-URL: Documentation, https://github.com/openverse-orca/OrcaLab
Project-URL: Repository, https://github.com/openverse-orca/OrcaLab
Project-URL: Bug Tracker, https://github.com/openverse-orca/OrcaLab/issues
Keywords: robotics,simulation,ui,asset-management,orca,pyside
Classifier: Development Status :: 4 - Beta
Classifier: Intended Audience :: Science/Research
Classifier: License :: OSI Approved :: MIT License
Classifier: Programming Language :: Python :: 3
Classifier: Programming Language :: Python :: 3.12
Classifier: Topic :: Scientific/Engineering :: Artificial Intelligence
Classifier: Topic :: Software Development :: User Interfaces
Requires-Python: >=3.12
Requires-Dist: orca-gym==26.1.8
Requires-Dist: pyside6==6.9.2
Requires-Dist: aiohttp==3.13.1
Requires-Dist: qasync==0.28.0
Requires-Dist: psutil==7.1.2
Requires-Dist: requests==2.32.5
Requires-Dist: pillow==12.0.0
Requires-Dist: pyparsing==3.2.5
Requires-Dist: matplotlib==3.10.7
Provides-Extra: dev
Requires-Dist: pytest; extra == "dev"
Requires-Dist: pytest-cov; extra == "dev"
Requires-Dist: flake8; extra == "dev"
Requires-Dist: black; extra == "dev"
Requires-Dist: mypy; extra == "dev"
